pytest_retry_class/__init__.py
pytest_retry_class/main.py
pytest_retry_class-0.2.0.dist-info/LICENSE
pytest_retry_class-0.2.0.dist-info/METADATA
pytest_retry_class-0.2.0.dist-info/WHEEL
pytest_retry_class-0.2.0.dist-info/entry_points.txt
pytest_retry_class-0.2.0.dist-info/top_level.txt
pytest_retry_class-0.2.0.dist-info/RECORD
